pirobot/.version
pirobot/__init__.py
pirobot/configs.json
pirobot/main.py
pirobot/pirobot.py
pirobot/quizzes.json
pirobot-1.9.3.dist-info/LICENSE
pirobot-1.9.3.dist-info/METADATA
pirobot-1.9.3.dist-info/WHEEL
pirobot-1.9.3.dist-info/entry_points.txt
pirobot-1.9.3.dist-info/top_level.txt
pirobot-1.9.3.dist-info/RECORD
