Metadata-Version: 2.1
Name: pirobot
Version: 1.9.3
Summary: Telegram Bot Script with Flood Control Functionality
Home-page: https://github.com/hk4crprasad/pirobot
Download-URL: https://github.com/hk4crprasad/pirobot/archive/pypi.zip
Author: HK4CRPRASAD
Author-email: hotahara12@gmail.com
License: GPL-3.0
Keywords: telegram,bot,pirobot,flood,auto-reply,telethon
Classifier: Development Status :: 4 - Beta
Classifier: Intended Audience :: Developers
Classifier: Topic :: Software Development :: Libraries :: Python Modules
Classifier: License :: OSI Approved :: GNU General Public License v3 (GPLv3)
Classifier: Programming Language :: Python :: 3
Classifier: Programming Language :: Python :: 3.6
Classifier: Programming Language :: Python :: 3.7
Classifier: Programming Language :: Python :: 3.8
Classifier: Programming Language :: Python :: 3.9
Classifier: Programming Language :: Python :: 3.10
Classifier: Programming Language :: Python :: 3.11
Classifier: Operating System :: OS Independent
Classifier: Topic :: Communications :: Chat
Requires-Python: >=3.6
License-File: LICENSE
Requires-Dist: telethon
Requires-Dist: python-dotenv
Requires-Dist: python-telegram-bot
Requires-Dist: requests
